{
	"build": {
		"context": "..",
		"dockerfile": "apps/chaos/Dockerfile"
	},
	"name": "Chaos",
	"settings": {
		"lldb.executable": "/usr/bin/lldb"
	},
	"extensions": [
		"rust-lang.rust",
		"bungcip.better-toml",
		"vadimcn.vscode-lldb"
	],
	"forwardPorts": [
		3000,
		4001,
		5001,
		6379,
		8080,
		9094,
		9096,
		9999
	],
	"onCreateCommand": [
		"rustup install toolchain nightly",
		"cargo build --release",
		"cargo check"
	],
	"postStartCommand": "./target/debug/chaos --dev --ws-external"
}

